llumo/__init__.py
llumo/callback.py
llumo/callbacks-0.py
llumo/chains.py
llumo/client.py
llumo/exceptions.py
llumo/execution.py
llumo/functionCalling.py
llumo/google.py
llumo/helpingFuntions.py
llumo/llumoLogger.py
llumo/llumoSessionContext.py
llumo/models.py
llumo/openai.py
llumo/sockets.py
llumo-0.2.45.dist-info/licenses/LICENSE
llumo-0.2.45.dist-info/METADATA
llumo-0.2.45.dist-info/WHEEL
llumo-0.2.45.dist-info/top_level.txt
llumo-0.2.45.dist-info/RECORD
